wexpect/__init__.py
wexpect/__main__.py
wexpect/__version__.py
wexpect/console_reader.py
wexpect/host.py
wexpect/legacy_wexpect.py
wexpect/wexpect_util.py
wexpect_uv-0.0.6.dist-info/METADATA
wexpect_uv-0.0.6.dist-info/WHEEL
wexpect_uv-0.0.6.dist-info/entry_points.txt
wexpect_uv-0.0.6.dist-info/licenses/LICENSE
wexpect_uv-0.0.6.dist-info/RECORD
