Metadata-Version: 2.4
Name: wexpect-uv
Version: 0.0.6
Summary: Windows alternative of pexpect rebuild by uv
Project-URL: Source Code, https://github.com/XnneHangLab/wexpect-uv
Author-email: "Noah Spurrier, Richard Holden, Marco Molteni, Kimberley Burchett, Robert Stone, Hartmut Goebel, Chad Schroeder, Erick Tryzelaar, Dave Kirby, Ids vander Molen, George Todd, Noel Taylor, Nicolas D. Cesar, Alexander Gattin, Geoffrey Marshall, Francisco Lourenco, Glen Mabey, Karthik Gurusamy, Fernando Perez, Corey Minyard, Jon Cohen, Guillaume Chazarain, Andrew Ryan, Nick Craig-Wood, Andrew Stone, Jorgen Grahn, Benedek Racz" <betontalpfa@gmail.com>, XnneHang <XnneHang@gmail.com>
License: MIT
License-File: LICENSE
Keywords: automation,expect,pexpect,scripting,wexpect
Classifier: Development Status :: 4 - Beta
Classifier: Environment :: Console
Classifier: Intended Audience :: Developers
Classifier: Intended Audience :: Information Technology
Classifier: Operating System :: Microsoft :: Windows
Classifier: Programming Language :: Python :: 3.9
Classifier: Programming Language :: Python :: 3.10
Classifier: Programming Language :: Python :: 3.11
Requires-Python: <3.14,>=3.9
Requires-Dist: psutil>=5.0.0
Requires-Dist: pywin32>=220
Requires-Dist: setuptools>=76.0.0
Requires-Dist: wcwidth>=0.2.13
